{
  "statusBarOrder": [],
  "ribbonBarOrder": [],
  "fileExplorerOrder": {
    "观影/中国奇谭": [
      "观影/中国奇谭/中国奇谭.md",
      "观影/中国奇谭/第一集小妖怪的夏天",
      "观影/中国奇谭/第二集鹅鹅鹅",
      "观影/中国奇谭/第三集 林林",
      "观影/中国奇谭/第四集 乡村巴士带走了王孩儿和神仙",
      "观影/中国奇谭/第五集 小满",
      "观影/中国奇谭/第六集 飞鸟与鱼",
      "观影/中国奇谭/第七集 小卖部",
      "观影/中国奇谭/第八集 玉兔",
      "观影/中国奇谭/其他想说的.md"
    ],
    "/": [
      "测试专用",
      "读书",
      "读书笔记",
      "观影",
      "其他想说的.md",
      "截图.png",
      "学习",
      "英语词义分类数据资料",
      "cedict_1_0_ts_utf-8_mdbg.txt.gz",
      "cedict_ts.u8",
      "Day Planners",
      "Pasted image 20230224155352.png",
      "Pasted image 20230224155423.png",
      "Screenshot_20221219_173156.png"
    ]
  },
  "actionBarOrder": {},
  "autoHide": true,
  "autoHideDelay": 200,
  "dragDelay": 200
}