{
  "confirmDeletion": true,
  "showAddCommand": true,
  "debug": false,
  "editorMenu": [
    {
      "id": "obsidian-to-notion:share-to-notion",
      "icon": "share-2",
      "name": "share to notion",
      "mode": "any"
    },
    {
      "id": "note-refactor-obsidian:app:split-note-by-heading-h1",
      "icon": "arrow-left-right",
      "name": "Note Refactor: Split note by headings - H1",
      "mode": "any"
    },
    {
      "id": "media-extended:open-media-link",
      "icon": "airplay",
      "name": "Media Extended: Open Media from Link",
      "mode": "any"
    }
  ],
  "fileMenu": [
    {
      "id": "note-refactor-obsidian:app:split-note-by-heading-h1",
      "icon": "arrow-left-right",
      "name": "Note Refactor: Split note by headings - H1",
      "mode": "any"
    }
  ],
  "leftRibbon": [],
  "rightRibbon": [],
  "titleBar": [],
  "statusBar": [],
  "pageHeader": [],
  "macros": [],
  "explorer": [],
  "hide": {
    "statusbar": [],
    "leftRibbon": []
  },
  "spacing": 8,
  "advancedToolbar": {
    "rowHeight": 48,
    "rowCount": 1,
    "spacing": 0,
    "buttonWidth": 48,
    "columnLayout": false,
    "mappedIcons": [],
    "tooltips": false,
    "heightOffset": 0
  }
}